icol/__init__.py
icol/icol.py
icol/logistic_icol.py
icol-0.8.5.dist-info/LICENSE
icol-0.8.5.dist-info/METADATA
icol-0.8.5.dist-info/WHEEL
icol-0.8.5.dist-info/top_level.txt
icol-0.8.5.dist-info/RECORD
