Metadata-Version: 2.1
Name: icol
Version: 0.8.5
Summary: Iterative Correlation Learning implementation
Author-email: Simon Teshuva <simon.teshuva@gmail.com>
License: MIT
Requires-Python: >=3.8
License-File: LICENSE
Requires-Dist: numpy>=1.24.3
Requires-Dist: scikit-learn>=1.2.2
